embantic/__init__.py
embantic/base.py
embantic/img.py
embantic/text.py
embantic-0.1.0.dist-info/LICENSE
embantic-0.1.0.dist-info/METADATA
embantic-0.1.0.dist-info/WHEEL
embantic-0.1.0.dist-info/RECORD
