Metadata-Version: 2.1
Name: embantic
Version: 0.1.0
Summary: Embed pydantic models
License: MIT
Author: Patrick Barker
Author-email: patrickbarkerco@gmail.com
Requires-Python: >=3.10,<4.0
Classifier: License :: OSI Approved :: MIT License
Classifier: Programming Language :: Python :: 3
Classifier: Programming Language :: Python :: 3.10
Classifier: Programming Language :: Python :: 3.11
Classifier: Programming Language :: Python :: 3.12
Requires-Dist: faiss-cpu (>=1.8.0.post1,<2.0.0)
Requires-Dist: pydantic (>=2.9.2,<3.0.0)
Requires-Dist: torch (>=2.4.1,<3.0.0)
Requires-Dist: torchvision (>=0.19.1,<0.20.0)
